setup.py
django_super_cms/__init__.py
django_super_cms/managers.py
django_super_cms/messages.py
django_super_cms/models.py
django_super_cms/tests.py
django_super_cms/urls.py
django_super_cms/utils.py
django_super_cms/validators.py
django_super_cms.egg-info/PKG-INFO
django_super_cms.egg-info/SOURCES.txt
django_super_cms.egg-info/dependency_links.txt
django_super_cms.egg-info/entry_points.txt
django_super_cms.egg-info/not-zip-safe
django_super_cms.egg-info/requires.txt
django_super_cms.egg-info/top_level.txt
django_super_cms/actions/__init__.py
django_super_cms/actions/account.py
django_super_cms/actions/admin.py
django_super_cms/init/__init__.py
django_super_cms/migrations/0001_initial.py
django_super_cms/migrations/0002_auto_20150325_0215.py
django_super_cms/migrations/0003_auto_20150326_0741.py
django_super_cms/migrations/0004_auto_20150326_0800.py
django_super_cms/migrations/0005_auto_20150327_0136.py
django_super_cms/migrations/__init__.py
django_super_cms/project/__init__.py
django_super_cms/project/manage.py
django_super_cms/project/media/__init__.py
django_super_cms/project/project/__init__.py
django_super_cms/project/project/settings.py
django_super_cms/project/project/urls.py
django_super_cms/project/project/wsgi.py
django_super_cms/project/static/__init__.py
django_super_cms/project/templates/__init__.py
django_super_cms/static/__init__.py
django_super_cms/templates/__init__.py
django_super_cms/templates/admin-ext/__init__.py
django_super_cms/views/__init__.py
django_super_cms/views/account.py
django_super_cms/views/admin.py
django_super_cms/views/main.py
django_super_cms/views/post.py
django_super_cms/views/utils.py