Metadata-Version: 1.1
Name: django-super-cms
Version: 0.1a2
Summary: a simple cms app for django , just for small site usage
Home-page: https://github.com/majia-tech/django-super-cms
Author: younger shen
Author-email: younger.x.shen@gmail.com
License: MIT
Keywords: django-super-cms,django,cms,django cms
Platform: UNKNOWN
Classifier: Development Status :: 2 - Pre-Alpha
Classifier: Environment :: Web Environment
Classifier: Framework :: Django
Classifier: Intended Audience :: Developers
Classifier: License :: OSI Approved :: MIT License
Classifier: Natural Language :: English
Classifier: Programming Language :: Python :: 2.7
